probe_utils/__init__.py
probe_utils/rap_utils.py
probeutils-1.0.4.dist-info/LICENSE
probeutils-1.0.4.dist-info/METADATA
probeutils-1.0.4.dist-info/WHEEL
probeutils-1.0.4.dist-info/top_level.txt
probeutils-1.0.4.dist-info/RECORD
