Metadata-Version: 2.1
Name: probeutils
Version: 1.0.4
Summary: A package for generating RAP probes.
Author: Drew Honson
Author-email: dhonson@lncrna.caltech.edu
Classifier: Programming Language :: Python :: 3
Classifier: Operating System :: OS Independent
License-File: LICENSE
